[
  {
    "uwfirstname": "Jacob",
    "uwlastname": "Sirmon",
    "uwposition": "QB",
    "uwstars": 4,
    "uwheight": "6-4",
    "uwweight": 226,
    "uwschool": "Bothell",
    "uwhometown": "Bothell",
    "uwsigned": "x"
  },
  {
    "uwfirstname": "Colson ",
    "uwlastname": "Yankoff",
    "uwposition": "QB",
    "uwstars": 4,
    "uwheight": "6-4",
    "uwweight": 204,
    "uwschool": "Coeur d'Alene",
    "uwhometown": "Coeur d'Alene, Idaho",
    "uwsigned": "x"
  },
  {
    "uwfirstname": "Richard",
    "uwlastname": "Newton",
    "uwposition": "RB",
    "uwstars": 3,
    "uwheight": "6-1",
    "uwweight": 183,
    "uwschool": "Palmdale",
    "uwhometown": "Palmdale, Calif.",
    "uwsigned": "x"
  },
  {
    "uwfirstname": "Trey",
    "uwlastname": "Lowe",
    "uwposition": "WR",
    "uwstars": 4,
    "uwheight": "5-7",
    "uwweight": 174,
    "uwschool": "Jesuit",
    "uwhometown": "Portland",
    "uwsigned": "x"
  },
  {
    "uwfirstname": "Austin ",
    "uwlastname": "Osborne",
    "uwposition": "WR",
    "uwstars": 4,
    "uwheight": "6-2",
    "uwweight": 188,
    "uwschool": "Mission Viejo",
    "uwhometown": "Mission Viejo, Calif.",
    "uwsigned": "x"
  },
  {
    "uwfirstname": "Marquis ",
    "uwlastname": "Spiker",
    "uwposition": "WR",
    "uwstars": 4,
    "uwheight": "6-3",
    "uwweight": 180,
    "uwschool": "Murrieta Valley",
    "uwhometown": "Murrieta, Calif.",
    "uwsigned": "x"
  },
  {
    "uwfirstname": "Devin",
    "uwlastname": "Culp",
    "uwposition": "TE",
    "uwstars": 3,
    "uwheight": "6-3",
    "uwweight": 235,
    "uwschool": "Gonzaga Prep",
    "uwhometown": "Spokane",
    "uwsigned": "x"
  },
  {
    "uwfirstname": "Ulumoo “M.J.”",
    "uwlastname": "Ale",
    "uwposition": "OL",
    "uwstars": 3,
    "uwheight": "6-6",
    "uwweight": 361,
    "uwschool": "Fife",
    "uwhometown": "Fife",
    "uwsigned": "x"
  },
  {
    "uwfirstname": "Victor",
    "uwlastname": "Curne",
    "uwposition": "OL",
    "uwstars": 3,
    "uwheight": "6-5",
    "uwweight": 313,
    "uwschool": "Second Baptist",
    "uwhometown": "Houston",
    "uwsigned": "x"
  },
  {
    "uwfirstname": "Matteo",
    "uwlastname": "Mele",
    "uwposition": "OL",
    "uwstars": 4,
    "uwheight": "6-6",
    "uwweight": 277,
    "uwschool": "Salpointe Catholic",
    "uwhometown": "Tucson, Ariz.",
    "uwsigned": "x"
  },
  {
    "uwfirstname": "Draco",
    "uwlastname": "Bynum",
    "uwposition": "DL",
    "uwstars": 4,
    "uwheight": "6-5",
    "uwweight": 250,
    "uwschool": "Wilsonville",
    "uwhometown": "Wilsonville, Ore.",
    "uwsigned": "x"
  },
  {
    "uwfirstname": "Mosiah",
    "uwlastname": "Nasili-Liu",
    "uwposition": "DL",
    "uwstars": 3,
    "uwheight": "6-3",
    "uwweight": 275,
    "uwschool": "Emerald Ridge",
    "uwhometown": "Puyallup",
    "uwsigned": "x"
  },
  {
    "uwfirstname": "Sam",
    "uwlastname": "Taimani",
    "uwposition": "DL",
    "uwstars": 4,
    "uwheight": "6-2",
    "uwweight": 320,
    "uwschool": "East",
    "uwhometown": "Salt Lake City",
    "uwsigned": "x"
  },
  {
    "uwfirstname": "Zion",
    "uwlastname": "Tupuola-Fetui",
    "uwposition": "DL/LB",
    "uwstars": 3,
    "uwheight": "6-2",
    "uwweight": 250,
    "uwschool": "Pearl City",
    "uwhometown": "Pearl City, Hawaii",
    "uwsigned": "x"
  },
  {
    "uwfirstname": "Ale \"Brandon\"",
    "uwlastname": "Kaho",
    "uwposition": "LB",
    "uwstars": 5,
    "uwheight": "6-1",
    "uwweight": 218,
    "uwschool": "Reno",
    "uwhometown": "Reno, Nev.",
    "uwsigned": "x"
  },
  {
    "uwfirstname": "Jackson",
    "uwlastname": "Sirmon",
    "uwposition": "LB",
    "uwstars": 4,
    "uwheight": "6-2",
    "uwweight": 224,
    "uwschool": "Brentwood Academy",
    "uwhometown": "Brentwood, Tenn.",
    "uwsigned": "x"
  },
  {
    "uwfirstname": "MJ",
    "uwlastname": "Tafisi",
    "uwposition": "LB",
    "uwstars": 3,
    "uwheight": "6-0",
    "uwweight": 224,
    "uwschool": "Alta",
    "uwhometown": "Sandy, Utah",
    "uwsigned": "x"
  },
  {
    "uwfirstname": "Dominique",
    "uwlastname": "Hampton",
    "uwposition": "CB",
    "uwstars": 3,
    "uwheight": "6-2",
    "uwweight": 197,
    "uwschool": "Centennial",
    "uwhometown": "Peoria, Ariz.",
    "uwsigned": "x"
  },
  {
    "uwfirstname": "Kyler",
    "uwlastname": "Gordon",
    "uwposition": "CB",
    "uwstars": 4,
    "uwheight": "5-10",
    "uwweight": 175,
    "uwschool": "Archbishop Murphy",
    "uwhometown": "Everett",
    "uwsigned": "x"
  },
  {
    "uwfirstname": "Julius",
    "uwlastname": "Irvin",
    "uwposition": "DB",
    "uwstars": 4,
    "uwheight": "6-2",
    "uwweight": 187,
    "uwschool": "Servite",
    "uwhometown": "Anaheim, Calif."
  }
]